<?xml version="1.0" encoding="UTF-8"?>
<song>
  <title>Szüntelen áldjuk az ég urát</title>
  <lyrics>[C]
 Alleluja, alleluja, alleluja, alleluja
 
[V1]
 Szüntelen áldjuk az ég Urát
 Együtt zengjünk alleluját!
 Itt van az óra, közel az idő
 Visszajön újra az Üdvözítő.
 
[V2]
 Messzire hangzik az égi szó:
 Üdvösségünk elérkezett.
 Krisztus az Úr, övé lett a hatalom,
 mert a mi vádlónk legyőzetett.
 
[V3]
 Minden szent és vértanú
 győztesként áll Isten előtt.
 Győztek a Bárány vére által
 s nem kímélték életük.

[V4]
 Örvendjen ma a föld s az ég,
 zengjük az Isten szent nevét!
 Krisztussal együtt áldjuk az Atyát:
 Őt, aki értünk adta Fiát.</lyrics>
  <author></author>
  <copyright></copyright>
  <hymn_number>036</hymn_number>
  <presentation></presentation>
  <ccli></ccli>
  <capo print="false"></capo>
  <key></key>
  <aka></aka>
  <key_line></key_line>
  <user1></user1>
  <user2></user2>
  <user3></user3>
  <theme></theme>
  <linked_songs/>
  <tempo></tempo>
  <time_sig></time_sig>
  <backgrounds resize="screen" keep_aspect="false" link="false" background_as_text="false"/>
</song>