<?xml version="1.0" encoding="UTF-8"?>
<song>
  <title>Veni Sancte Spiritus</title>
  <lyrics>[C]
 Veni Sancte Spiritus!
 Veni Sancte Spiritus!
 
[V1]
 Jöjj tüzeddel,
 jöjj mutasd meg szeretetedet,
 jöjj a szomjunkat oltsd!
 Töltsd be életünk
 s a szívünk a Te fényeddel!
 Jöjj, hogy lángoljon a tűz!
 
[V2]
 Jöjj, kegyelmeddel töltsél el:
 tisztítsd a szívünk!
 Mosd meg, ami szennyezett!
 Jöjj, siess, a gyöngeségünkben
 Te adj erőt!
 Jöjj, hogy lángoljon a tűz!
 
[V3]
 Jöjj, mutasd meg nekünk a Fiút
 és az Atyát! Éleszd újra a hitünk!
 Jöjj, ajándékaidat most
 bőkezűen oszd!
 Jöjj, hogy lángoljon a tűz!
</lyrics>
  <author></author>
  <copyright></copyright>
  <hymn_number>303</hymn_number>
  <presentation></presentation>
  <ccli></ccli>
  <capo print="false"></capo>
  <key></key>
  <aka></aka>
  <key_line></key_line>
  <user1></user1>
  <user2></user2>
  <user3></user3>
  <theme></theme>
  <linked_songs/>
  <tempo></tempo>
  <time_sig></time_sig>
  <backgrounds resize="screen" keep_aspect="false" link="false" background_as_text="false"/>
</song>